mlops_wrapper/__init__.py
mlops_wrapper/config.py
mlops_wrapper/mlflow_wrapper.py
mlops_wrapper/experiments/__init__.py
mlops_wrapper/experiments/base_experiment.py
mlops_wrapper-0.1.4.dist-info/licenses/LICENSE
mlops_wrapper-0.1.4.dist-info/METADATA
mlops_wrapper-0.1.4.dist-info/WHEEL
mlops_wrapper-0.1.4.dist-info/top_level.txt
mlops_wrapper-0.1.4.dist-info/RECORD
