Metadata-Version: 2.4
Name: mlops_wrapper
Version: 0.1.4
Summary: a unified mlflow wrapper for standardized ML model logging and registration.
Author-email: akaay <s.a.ashok91@gmail.com>
License: MIT License
Project-URL: Homepage, https://github.com/copernicium-112/mlops_wrapper
Project-URL: Issues, https://github.com/copernicium-112/mlops_wrapper/issues
Requires-Python: >=3.8
License-File: LICENSE
Requires-Dist: mlflow>=1.0.0
Requires-Dist: boto3>=1.0.0
Dynamic: license-file
